drestful/__init__.py
drestful/api.py
drestful-0.1.dist-info/METADATA
drestful-0.1.dist-info/RECORD
drestful-0.1.dist-info/WHEEL
drestful-0.1.dist-info/top_level.txt
