Metadata-Version: 2.1
Name: drestful
Version: 0.1
Summary: create simple django restful api
Home-page: https://github.com/pochnsong/drestful
Author: song.zirui
Author-email: pochnsong@163.com
License: UNKNOWN
Platform: UNKNOWN
Classifier: Programming Language :: Python :: 3
Classifier: License :: OSI Approved :: MIT License
Classifier: Operating System :: OS Independent
